stsb3/__init__.py
stsb3/constants.py
stsb3/core.py
stsb3/effects.py
stsb3/exceptions.py
stsb3/sts.py
stsb3/util.py
stsb3-0.2.0.dist-info/LICENSE
stsb3-0.2.0.dist-info/METADATA
stsb3-0.2.0.dist-info/WHEEL
stsb3-0.2.0.dist-info/top_level.txt
stsb3-0.2.0.dist-info/RECORD
