Metadata-Version: 2.1
Name: stsb3
Version: 0.2.0
Summary: Structural time series building blocks
Home-page: https://gitlab.com/daviddewhurst/stsb3
Author: David Dewhurst
Author-email: drd@davidrushingdewhurst.com
License: MIT
Platform: UNKNOWN
Classifier: Development Status :: 2 - Pre-Alpha
Classifier: Intended Audience :: Science/Research
Classifier: Intended Audience :: Financial and Insurance Industry
Classifier: License :: OSI Approved :: MIT License
Classifier: Operating System :: POSIX
Classifier: Topic :: Scientific/Engineering :: Artificial Intelligence
Requires-Dist: black
Requires-Dist: numpy
Requires-Dist: opt-einsum
Requires-Dist: pyflakes
Requires-Dist: pyro-api
Requires-Dist: pyro-ppl
Requires-Dist: pytest
Requires-Dist: torch
Requires-Dist: virtualenv
